yq/__init__.py
yq/__main__.py
yq/dumper.py
yq/loader.py
yq/parser.py
yq/version.py
yq/tomlq/__init__.py
yq/tomlq/__main__.py
yq/xq/__init__.py
yq/xq/__main__.py
yq-3.4.2.dist-info/LICENSE
yq-3.4.2.dist-info/METADATA
yq-3.4.2.dist-info/WHEEL
yq-3.4.2.dist-info/entry_points.txt
yq-3.4.2.dist-info/top_level.txt
yq-3.4.2.dist-info/RECORD
