Metadata-Version: 2.1
Name: yq
Version: 3.4.2
Summary: Command-line YAML/XML processor - jq wrapper for YAML/XML documents
Home-page: https://github.com/kislyuk/yq
Author: Andrey Kislyuk
Author-email: kislyuk@gmail.com
License: Apache Software License
Classifier: Intended Audience :: Developers
Classifier: License :: OSI Approved :: Apache Software License
Classifier: Operating System :: MacOS :: MacOS X
Classifier: Operating System :: POSIX
Classifier: Programming Language :: Python
Classifier: Programming Language :: Python :: 3
Classifier: Programming Language :: Python :: 3.8
Classifier: Programming Language :: Python :: 3.9
Classifier: Programming Language :: Python :: 3.10
Classifier: Programming Language :: Python :: 3.11
Classifier: Programming Language :: Python :: 3.12
Classifier: Topic :: Software Development :: Libraries :: Python Modules
Requires-Python: >=3.6
License-File: LICENSE
Requires-Dist: PyYAML >=5.3.1
Requires-Dist: xmltodict >=0.11.0
Requires-Dist: tomlkit >=0.11.6
Requires-Dist: argcomplete >=1.8.1
Provides-Extra: tests
Requires-Dist: coverage ; extra == 'tests'
Requires-Dist: wheel ; extra == 'tests'
Requires-Dist: build ; extra == 'tests'
Requires-Dist: ruff ; extra == 'tests'
Requires-Dist: mypy ; extra == 'tests'
